{"id":"9cbcf7f1-733c-49c5-ac01-a3c145483fce","fileName":"worker-listener.kts","functionName":"jobsListener","params":{"arg0":"9","arg1":"\"Jacob\"","arg2":"{\"jobId\":\"c95d09fb-07be-4c6f-89b4-a4881987b669\",\"queue\":\"default\",\"driver\":\"file\",\"function\":\"registerIglyUser\",\"context\":\"default\",\"contextVersion\":\"1757031492671\",\"origin\":\"koupper\",\"packageName\":\"com.igly.comms.scripts\",\"scriptPath\":\"/C:/Users/dosek/develop/igly-comms/build/classes/kotlin/main/\",\"finishedAt\":1758401422222}"},"signature":{"first":["Int","String","JobEvent"],"second":"String"},"scriptPath":"C:\\Users\\dosek\\develop\\igly-comms\\worker-listener.kts","packageName":null,"origin":"koupper","context":"C:\\Users\\dosek\\develop\\igly-comms","sourceType":"script","queue":"job-callbacks","driver":"file","contextVersion":"unknown","sourceSnapshot":"import com.koupper.octopus.annotations.Export\r\nimport com.koupper.octopus.annotations.Logger\r\nimport com.koupper.octopus.annotations.JobsListener\r\nimport com.koupper.octopus.process.JobEvent\r\nimport com.koupper.logging.GlobalLogger.log\r\n\r\n@JobsListener\r\n@Export\r\n@Logger(destination = \"file:example[yyy-MM-dd]\", level = \"INFO\")\r\nval jobsListener: (Int, String, JobEvent) -> String = { a, b, c ->\r\n    log.info { \"Procesando JobEvent con id=${a}\" }\r\n    \"joder tio\"\r\n}\r\n\r\n","artifactUri":null,"artifactSha256":null}